bdnb_api/__init__.py
bdnb_api/_base_client.py
bdnb_api/_client.py
bdnb_api/_compat.py
bdnb_api/_constants.py
bdnb_api/_exceptions.py
bdnb_api/_files.py
bdnb_api/_models.py
bdnb_api/_qs.py
bdnb_api/_resource.py
bdnb_api/_response.py
bdnb_api/_streaming.py
bdnb_api/_types.py
bdnb_api/_version.py
bdnb_api/pagination.py
bdnb_api/py.typed
bdnb_api/_utils/__init__.py
bdnb_api/_utils/_logs.py
bdnb_api/_utils/_proxy.py
bdnb_api/_utils/_reflection.py
bdnb_api/_utils/_streams.py
bdnb_api/_utils/_sync.py
bdnb_api/_utils/_transform.py
bdnb_api/_utils/_typing.py
bdnb_api/_utils/_utils.py
bdnb_api/lib/.keep
bdnb_api/resources/__init__.py
bdnb_api/resources/autocompletion.py
bdnb_api/resources/donnees/__init__.py
bdnb_api/resources/donnees/adresse.py
bdnb_api/resources/donnees/ancqpv.py
bdnb_api/resources/donnees/batiment_groupe.py
bdnb_api/resources/donnees/batiment_groupe_adresse.py
bdnb_api/resources/donnees/batiment_groupe_argiles.py
bdnb_api/resources/donnees/batiment_groupe_bdtopo_bat.py
bdnb_api/resources/donnees/batiment_groupe_bdtopo_equ.py
bdnb_api/resources/donnees/batiment_groupe_bdtopo_zoac.py
bdnb_api/resources/donnees/batiment_groupe_bpe.py
bdnb_api/resources/donnees/batiment_groupe_delimitation_enveloppe.py
bdnb_api/resources/donnees/batiment_groupe_dle_elec_2020.py
bdnb_api/resources/donnees/batiment_groupe_dle_elec_multimillesime.py
bdnb_api/resources/donnees/batiment_groupe_dle_gaz_2020.py
bdnb_api/resources/donnees/batiment_groupe_dle_gaz_multimillesime.py
bdnb_api/resources/donnees/batiment_groupe_dle_reseaux_2020.py
bdnb_api/resources/donnees/batiment_groupe_dle_reseaux_multimillesime.py
bdnb_api/resources/donnees/batiment_groupe_dpe_representatif_logement.py
bdnb_api/resources/donnees/batiment_groupe_dpe_statistique_logement.py
bdnb_api/resources/donnees/batiment_groupe_dvf_open_representatif.py
bdnb_api/resources/donnees/batiment_groupe_dvf_open_statistique.py
bdnb_api/resources/donnees/batiment_groupe_ffo_bat.py
bdnb_api-0.1.0a5.dist-info/METADATA
bdnb_api-0.1.0a5.dist-info/WHEEL
bdnb_api-0.1.0a5.dist-info/licenses/LICENSE
bdnb_api-0.1.0a5.dist-info/RECORD
